classic/falcon_integration/__init__.py
classic/falcon_integration/error_handlers.py
classic/falcon_integration/registration.py
classic/falcon_integration/serialization.py
classic/falcon_integration/specification.py
classic/http_api/__init__.py
classic/http_api/app.py
classic/http_api/error_handlers.py
classic/http_api/specification.py
classic/http_api/authentication/__init__.py
classic/http_api/authentication/base.py
classic/http_api/authentication/fallback.py
classic/http_api/authentication/jwt_.py
classic_falcon_integration-1.0.1.dist-info/licenses/LICENSE
classic_falcon_integration-1.0.1.dist-info/METADATA
classic_falcon_integration-1.0.1.dist-info/WHEEL
classic_falcon_integration-1.0.1.dist-info/top_level.txt
classic_falcon_integration-1.0.1.dist-info/RECORD
