Metadata-Version: 2.4
Name: classic-falcon-integration
Version: 1.0.1
Summary: Provides integrations of classic libs with Falcon web framework
Author-email: Sergey Variasov <variasov@gmail.com>
Project-URL: Homepage, https://github.com/variasov/classic-falcon-integration
Requires-Python: >=3.10
License-File: LICENSE
Requires-Dist: falcon~=3.1
Requires-Dist: orjson~=3.10
Requires-Dist: classic-error-handling~=0.2
Requires-Dist: pydantic~=2.11
Requires-Dist: spectree~=1.5
Provides-Extra: dev
Requires-Dist: build~=1.2.2.post1; extra == "dev"
Requires-Dist: pytest==8.3.4; extra == "dev"
Requires-Dist: pytest-cov==6.0.0; extra == "dev"
Requires-Dist: twine~=4.0; extra == "dev"
Dynamic: license-file
